feabas/__init__.py
feabas/aligner.py
feabas/caching.py
feabas/common.py
feabas/concurrent.py
feabas/config.py
feabas/constant.py
feabas/dal.py
feabas/logging.py
feabas/matcher.py
feabas/material.py
feabas/mesh.py
feabas/mipmap.py
feabas/multisem.py
feabas/optimizer.py
feabas/renderer.py
feabas/spatial.py
feabas/stitcher.py
feabas/storage.py
feabas/thumbnail.py
feabas/visualization.py
feabas-3.0.2.dist-info/LICENSE
feabas-3.0.2.dist-info/METADATA
feabas-3.0.2.dist-info/WHEEL
feabas-3.0.2.dist-info/top_level.txt
feabas-3.0.2.dist-info/RECORD
