Metadata-Version: 2.1
Name: feabas
Version: 3.0.2
Summary: A python library for stitching & alignment of connectome datasets using finite-element method.
Author: Yuelong Wu
Author-email: yuelong.wu.2017@gmail.com
License: MIT
Classifier: Development Status :: 4 - Beta
Classifier: Intended Audience :: Science/Research
Classifier: Programming Language :: Python :: 3
Requires-Python: >=3.8
License-File: LICENSE
Requires-Dist: dask[array,diagnostics,distributed]
Requires-Dist: dask-jobqueue
Requires-Dist: dill
Requires-Dist: google-cloud-storage
Requires-Dist: h5py
Requires-Dist: numpy <2
Requires-Dist: opencv-python
Requires-Dist: psutil
Requires-Dist: pyyaml
Requires-Dist: rtree
Requires-Dist: scikit-image
Requires-Dist: scipy
Requires-Dist: shapely >=2.0.0
Requires-Dist: tensorstore
Requires-Dist: triangle
Requires-Dist: matplotlib
